{
    "data": [
        {
            "name": "PANASONIC MANUFACTURING PHILIPPINES CORPORATION",
            "address": "Ortigas Avenue, Extension, Taytay, Rizal, Philippines",
            "phone": "(+63) 2 8635-2260",
            "website": "https://www.panasonic.com/ph/",
            "image": "panasonic.web",
            "membershipLevel": "gold.webp",
            "membership": "Gold"
        },
        {
            "name": "PHILIPPINE SKYBIRD INDUSTRIAL CORPORATION",
            "address": "Taytay, Rizal, Philippines",
            "phone": "(+63) 8693-6560",
            "website": "http://skybirdph.com/",
            "image": "skybird.webp",
            "membershipLevel": "silver.webp",
            "membership": "Silver"
            
        },
        {
            "name": "CROWNMIX CORPORATION",
            "address": "Sitio Ilog Pugad, Hi-Way 2000 Taytay Rizal, Philippines",
            "phone": "(+63) 9162474091",
            "website": "https://crownmixcorp.com/",
            "image": "crownmix.webp",
            "membershipLevel": "np.webp",
            "membership": "NP"
        },
        {
            "name": "GL PACKAGING PHILIPPINES, INC.",
            "address": "PSPC Refinery Compound Brgy. Malaya, Pililla, Philippines",
            "phone": "(+63) 789-0123",
            "website": "https://www.glpackaging.ph/",
            "image": "GL Packaging.webp",
            "membershipLevel": "gold.webp",
            "membership": "Gold"
        },
        {
            "name": "GRANDSPAN DEVELOPMENT CORPORATION",
            "address": "Brgy. Tagpos, Binangonan Rizal 1940, Philippines",
            "phone": "(632) 8651-1451",
            "website": "https://www.grandspan.ph/home/",
            "image": "grandspan.webp",
            "membershipLevel": "bronze.webp",
            "membership": "Bronze"
        },
        {
            "name": "AMSTEEL STRUCTURES, INC.",
            "address": "88-98 Velesquez St.Taytay, Rizal, Philippines",
            "phone": "+632 8451 0191",
            "website": "http://amsteelstructures.com/",
            "image": "AMSTEEL.webp",
            "membershipLevel": "np.webp",
            "membership": "NP"
        },
        {
            "name": "DELTA CONCRETE CORPORATION",
            "address": "Velasquesz St. Sitio Bangiad Brgy. San Juan, Taytay Rizal, Philippines",
            "phone": "(02)8424-0980",
            "website": "https://deltaconcrete.com.ph/",
            "image": "delta.webp",
            "membershipLevel": "silver.webp",
            "membership": "Silver"
        },
        {
            "name": "KALINISAN CHEMICALS CORPORATION",
            "address": "Bldg 1 Cainta Business Center Executive Village Cainta, Rizal, Philippines",
            "phone": "(02) 8236-0332",
            "website": "https://kalinisanchemicals.com/",
            "image": "kalinisan.webp",
            "membershipLevel": "bronze.webp",
            "membership": "Bronze"
        }
    ]
}